{
  "name": "alcatel OT-799 Play",
  "description": "alcatel OT-799 Play phone. Announced 2011, February. Features 2.4″ TFT display, 2 MP camera, Bluetooth.",
  "url": "http://www.gsmarena.com/alcatel_ot_799_play-3802.php",
  "imageUrl": "http://cdn2.gsmarena.com/vv/bigpic/alcatel-onetouch799.jpg",
  "Network": {
    "Technology": "GSM",
    "2G bands": "GSM 850 / 1900",
    "Others": "GSM 900 / 1800",
    "GPRS": "Class 12",
    "EDGE": "Class 12"
  },
  "Launch": {
    "Announced": "2011, February",
    "Status": "Available. Released 2011, Q3"
  },
  "Body": {
    "Dimensions": "111 x 58.2 x 14 mm (4.37 x 2.29 x 0.55 in)",
    "Weight": "100.6 g (3.53 oz)",
    "Keyboard": "QWERTY",
    "SIM": "Mini-SIM"
  },
  "Display": {
    "Type": "TFT, 65K colors",
    "Size": "2.4 inches (~27.6% screen-to-body ratio)",
    "Resolution": "320 x 240 pixels (~167 ppi pixel density)"
  },
  "Platform": {
    "CPU": "208 MHz"
  },
  "Memory": {
    "Card slot": "microSD, up to 8 GB (dedicated slot)",
    "Phonebook": "Yes, Photocall",
    "Call records": "Yes",
    "Internal": "70 MB"
  },
  "Camera": {
    "Primary": "2 MP",
    "Video": "Yes",
    "Secondary": "No"
  },
  "Sound": {
    "Alert types": "Vibration; MP3 ringtones",
    "Loudspeaker ": "Yes",
    "3.5mm jack ": "No"
  },
  "Comms": {
    "WLAN": "No",
    "Bluetooth": "v2.0, A2DP",
    "GPS": "No",
    "Radio": "Stereo FM radio, RDS",
    "USB": "microUSB v2.0"
  },
  "Features": {
    "Messaging": "SMS, MMS, Email, IM",
    "Browser": "WAP 2.0/xHTML, HTML",
    "Games": "Yes",
    "Java": "Yes, MIDP 2.1",
    "Others": [
      "SNS integration",
      "MP3/AAC+/WAV/WMA player",
      "MP4/H.264 player",
      "Organizer",
      "Voice memo",
      "Predictive text input"
    ]
  },
  "Battery": {
    "Others": "Removable Li-Ion 850 mAh battery",
    "Stand-by": "Up to 600 h",
    "Talk time": "Up to 10 h",
    "Music play": "Up to 16 h"
  },
  "Misc": {
    "Colors": "Black/red, Cherry/red"
  }
}