{
  "name": "BQ  Aquaris M10",
  "description": "BQ  Aquaris M10 Android tablet. Announced 2015. Features 10.1″ Capacitive touchscreen, 5 MP camera, Wi-Fi, GPS, Bluetooth.",
  "url": "http://www.gsmarena.com/bq__aquaris_m10-7842.php",
  "imageUrl": "http://cdn2.gsmarena.com/vv/bigpic/bq-m10.jpg",
  "Network": {
    "Technology": "No cellular connectivity",
    "2G bands": "N/A",
    "GPRS": "No",
    "EDGE": "No"
  },
  "Launch": {
    "Announced": "2015",
    "Status": "Available. Released 2015"
  },
  "Body": {
    "Dimensions": "246 x 171 x 8.2 mm (9.69 x 6.73 x 0.32 in)",
    "Weight": "470 g (1.04 lb)",
    "SIM": "No"
  },
  "Display": {
    "Type": "Capacitive touchscreen, 16M colors",
    "Size": "10.1 inches (~70.3% screen-to-body ratio)",
    "Resolution": "800 x 1280 pixels (~149 ppi pixel density)",
    "Multitouch": "Yes, up to 10 fingers"
  },
  "Platform": {
    "OS": "Android OS, v5.1 (Lollipop)",
    "Chipset": "Mediatek MT8163B",
    "CPU": "Quad-core 1.3 GHz Cortex-A53",
    "GPU": "Mali-T720MP2"
  },
  "Memory": {
    "Card slot": "microSD, up to 64 GB (dedicated slot)",
    "Internal": "16 GB, 2 GB RAM"
  },
  "Camera": {
    "Primary": "5 MP",
    "Features": "Yes",
    "Video": "1080p",
    "Secondary": "2 MP"
  },
  "Sound": {
    "Alert types": "Vibration; MP3, WAV ringtones",
    "Loudspeaker ": "Yes, with stereo speakers",
    "3.5mm jack ": "Yes",
    "Others": "- Dolby Atmos sound"
  },
  "Comms": {
    "WLAN": "Wi-Fi 802.11 b/g/n",
    "Bluetooth": "v4.0",
    "GPS": "Yes",
    "Radio": "FM radio",
    "USB": "microUSB v2.0, USB On-The-Go"
  },
  "Features": {
    "Sensors": "Accelerometer, compass",
    "Messaging": "Email, Push Mail, IM",
    "Browser": "HTML5",
    "Java": "No",
    "Others": [
      "HDMI port",
      "MP3/WAV/eAAC+/Flac player",
      "MP4/H.264 player",
      "Document viewer",
      "Photo/video editor"
    ]
  },
  "Battery": {
    "Others": "Non-removable Li-Po 7280 mAh battery",
    "Talk time": "Up to 10 h (multimedia)",
    "Music play": "Up to 60 h"
  },
  "Misc": {
    "Colors": "Black, White",
    "SAR EU": "1.03 W/kg (body)",
    "Price group": "5/10 (About 230 EUR)"
  }
}