{
  "name": "Garmin-Asus Rainbow Lite 4G",
  "description": "Wiko Rainbow Lite 4G Android smartphone. Announced 2015, August. Features 3G, 5.0″ IPS LCD capacitive touchscreen, 5 MP camera, Wi-Fi, GPS, Bluetooth.",
  "url": "http://www.gsmarena.com/wiko_rainbow_lite_4g-7624.php",
  "imageUrl": "http://cdn2.gsmarena.com/vv/bigpic/wiko-rainbow-lite-4g.jpg",
  "Network": {
    "Technology": "GSM / HSPA / LTE",
    "2G bands": "GSM 850 / 900 / 1800 / 1900 - SIM 1 & SIM 2",
    "3G bands": "HSDPA 900 / 1900 / 2100",
    "4G bands": "LTE band 1(2100), 3(1800), 7(2600), 20(800)",
    "Speed": "HSPA 21.1/5.76 Mbps, LTE Cat4 150/50 Mbps",
    "GPRS": "Up to 107 kbps",
    "EDGE": "Up to 296 kbps"
  },
  "Launch": {
    "Announced": "2015, August",
    "Status": "Available. Released 2015, August"
  },
  "Body": {
    "Dimensions": "143 x 71.2 x 9 mm (5.63 x 2.80 x 0.35 in)",
    "Weight": "158 g (5.57 oz)",
    "SIM": "Dual SIM (Micro-SIM, dual stand-by)"
  },
  "Display": {
    "Type": "IPS LCD capacitive touchscreen, 16M colors",
    "Size": "5.0 inches (~67.7% screen-to-body ratio)",
    "Resolution": "480 x 854 pixels (~196 ppi pixel density)",
    "Multitouch": "Yes"
  },
  "Platform": {
    "OS": "Android OS, v5.1 (Lollipop)",
    "Chipset": "Qualcomm MSM8909 Snapdragon 210",
    "CPU": "Quad-core 1.1 GHz Cortex-A7",
    "GPU": "Adreno 304"
  },
  "Memory": {
    "Card slot": "microSD, up to 64 GB",
    "Internal": "4 GB, 1 GB RAM"
  },
  "Camera": {
    "Primary": "5 MP, autofocus, LED flash",
    "Features": "Geo-tagging, touch focus, HDR",
    "Video": "720p@30fps",
    "Secondary": "2 MP"
  },
  "Sound": {
    "Alert types": "Vibration; MP3, WAV ringtones",
    "Loudspeaker ": "Yes, with stereo speakers",
    "3.5mm jack ": "Yes"
  },
  "Comms": {
    "WLAN": "Wi-Fi 802.11 b/g/n, Wi-Fi Direct, hotspot",
    "Bluetooth": "v4.0, A2DP",
    "GPS": "Yes, with A-GPS",
    "Radio": "FM radio",
    "USB": "microUSB v2.0"
  },
  "Features": {
    "Sensors": "Accelerometer, proximity",
    "Messaging": "SMS (threaded view), MMS, Email, IM, Push Email",
    "Browser": "HTML5",
    "Java": "No",
    "Others": [
      "MP4/H.264 player",
      "MP3/AAC/WAV player",
      "Photo/video editor",
      "Document viewer"
    ]
  },
  "Battery": {
    "Others": "Removable Li-Ion 2000 mAh battery",
    "Stand-by": "Up to 144 h (2G) / Up to 144 h (3G)",
    "Talk time": "Up to 11 h 40 min (2G) / Up to 13 h 10 min (3G)"
  },
  "Misc": {
    "Colors": "Black, White, Coral, Bleen, Blue",
    "SAR EU": "0.17 W/kg (head)     0.47 W/kg (body)"
  }
}