{
  "name": "LG G2 Lite",
  "description": "LG G2 Lite Android smartphone. Announced 2014, November. Features 3G, 4.5″ IPS LCD capacitive touchscreen, 8 MP camera, Wi-Fi, GPS, Bluetooth.",
  "url": "http://www.gsmarena.com/lg_g2_lite-6776.php",
  "imageUrl": "http://cdn2.gsmarena.com/vv/bigpic/lg-g2-lite-d295.jpg",
  "Network": {
    "Technology": "GSM / HSPA",
    "2G bands": "GSM 850 / 900 / 1800 / 1900 - SIM 1 & SIM 2",
    "3G bands": "HSDPA 850 / 2100",
    "Speed": "HSPA",
    "GPRS": "Yes",
    "EDGE": "Yes"
  },
  "Launch": {
    "Announced": "2014, November",
    "Status": "Available. Released 2014, November"
  },
  "Body": {
    "Dimensions": "127.5 x 67.9 x 11.9 mm (5.02 x 2.67 x 0.47 in)",
    "Weight": "153.7 g (5.40 oz)",
    "SIM": "Dual SIM (dual stand-by)"
  },
  "Display": {
    "Type": "IPS LCD capacitive touchscreen, 16M colors",
    "Size": "4.5 inches (~66.6% screen-to-body ratio)",
    "Resolution": "480 x 800 pixels (~207 ppi pixel density)",
    "Multitouch": "Yes"
  },
  "Platform": {
    "OS": "Android OS, v4.4.2 (KitKat)",
    "CPU": "Quad-core 1.2 GHz"
  },
  "Memory": {
    "Card slot": "microSD, up to 32 GB (dedicated slot), 4 GB included",
    "Internal": "4 GB, 1 GB RAM"
  },
  "Camera": {
    "Primary": "8 MP, LED flash",
    "Features": "Geo-tagging",
    "Video": "480p",
    "Secondary": "VGA"
  },
  "Sound": {
    "Alert types": "Vibration; MP3, WAV ringtones",
    "Loudspeaker ": "Yes",
    "3.5mm jack ": "Yes"
  },
  "Comms": {
    "WLAN": "Yes",
    "Bluetooth": "v4.0, A2DP",
    "GPS": "Yes, with A-GPS",
    "Radio": "FM radio",
    "USB": "microUSB v2.0"
  },
  "Features": {
    "Sensors": "Accelerometer, proximity",
    "Messaging": "SMS(threaded view), MMS, Email, Push Mail, IM",
    "Browser": "HTML5",
    "Java": "No",
    "Others": [
      "MP4/H.264 player",
      "MP3/WAV/FLAC/eAAC+ player",
      "Photo editor",
      "Document viewer",
      "Voice memo/dial/commands"
    ]
  },
  "Battery": {
    "Others": "Removable Li-Ion 1820 mAh battery",
    "Stand-by": "Up to 345 h (2G) / Up to 345 h (3G)",
    "Talk time": "Up to 15 h (2G) / Up to 11 h 30 min (3G)"
  },
  "Misc": {
    "Colors": "White, Black, Gold",
    "SAR EU": "0.75 W/kg (head)     0.67 W/kg (body)",
    "Price group": "2/10 (About 100 EUR)"
  }
}