{
  "name": "Sharp Mi-451 Smartflo Poise",
  "description": "Spice Mi-451 Smartflo Poise Android smartphone. Announced 2014, February. Features 4.5″ IPS LCD capacitive touchscreen, 3.15 MP camera, Wi-Fi, GPS, Bluetooth.",
  "url": "http://www.gsmarena.com/spice_mi_451_smartflo_poise-6317.php",
  "imageUrl": "http://cdn2.gsmarena.com/vv/bigpic/spice-451.jpg",
  "Network": {
    "Technology": "GSM",
    "2G bands": "GSM 850 / 900 / 1800 / 1900 - SIM 1 & SIM 2",
    "GPRS": "Class 12",
    "EDGE": "Class 32"
  },
  "Launch": {
    "Announced": "2014, February",
    "Status": "Available. Released 2014, June"
  },
  "Body": {
    "Dimensions": "134.5 x 69.5 x 8.7 mm (5.30 x 2.74 x 0.34 in)",
    "Weight": "156 g (5.50 oz)",
    "SIM": "Dual SIM (Mini-SIM)"
  },
  "Display": {
    "Type": "IPS LCD capacitive touchscreen",
    "Size": "4.5 inches (~59.7% screen-to-body ratio)",
    "Resolution": "480 x 854 pixels (~218 ppi pixel density)",
    "Multitouch": "Yes"
  },
  "Platform": {
    "OS": "Android OS, v4.2 (Jelly Bean)"
  },
  "Memory": {
    "Card slot": "microSD, up to 32 GB"
  },
  "Camera": {
    "Primary": "3.15 MP",
    "Video": "Yes",
    "Secondary": "1.3 MP"
  },
  "Sound": {
    "Alert types": "Vibration; MP3, WAV ringtones",
    "Loudspeaker ": "Yes",
    "3.5mm jack ": "Yes"
  },
  "Comms": {
    "WLAN": "Yes",
    "Bluetooth": "v4.0",
    "GPS": "A-GPS only",
    "Radio": "FM radio",
    "USB": "microUSB"
  },
  "Features": {
    "Sensors": "Accelerometer",
    "Messaging": "SMS(threaded view), MMS, Email, Push Email, IM",
    "Browser": "HTML",
    "Java": "No",
    "Others": [
      "MP4/WMV/H.263 player",
      "MP3/WAV/AAC+ player",
      "Photo/video editor",
      "Voice memo"
    ]
  },
  "Battery": {
    "Others": "Removable Li-Ion 1450 mAh battery",
    "Talk time": "Up to 5 h 30 min"
  },
  "Misc": {
    "Colors": "White",
    "Price group": "2/10 (About 60 EUR)"
  }
}