{
  "name": "Telit i625",
  "description": "verykool i625 phone. Announced 2012, October. Features 2.3″ TFT display, 1.3 MP camera, Wi-Fi, Bluetooth.",
  "url": "http://www.gsmarena.com/verykool_i625-5050.php",
  "imageUrl": "http://cdn2.gsmarena.com/vv/bigpic/verykool-i625.jpg",
  "Network": {
    "Technology": "GSM",
    "2G bands": "GSM 850 / 900 / 1800 / 1900 - SIM 1 & SIM 2",
    "GPRS": "Yes",
    "EDGE": "No"
  },
  "Launch": {
    "Announced": "2012, October",
    "Status": "Available. Released 2012, October"
  },
  "Body": {
    "Dimensions": "111 x 58.4 x 11.2 mm (4.37 x 2.30 x 0.44 in)",
    "Weight": "110 g (3.88 oz)",
    "Keyboard": "QWERTY",
    "SIM": "Dual SIM (Mini-SIM)",
    "Others": "- Flashlight"
  },
  "Display": {
    "Type": "TFT",
    "Size": "2.3 inches (~25.3% screen-to-body ratio)",
    "Resolution": "320 x 240 pixels (~174 ppi pixel density)"
  },
  "Memory": {
    "Card slot": "microSD, up to 32 GB (dedicated slot)",
    "Phonebook": "Yes",
    "Call records": "Yes"
  },
  "Camera": {
    "Primary": "1.3 MP",
    "Secondary": "No"
  },
  "Sound": {
    "Alert types": "Vibration; Polyphonic",
    "Loudspeaker ": "Yes",
    "3.5mm jack ": "Yes"
  },
  "Comms": {
    "WLAN": "Yes",
    "Bluetooth": "v2.0, A2DP",
    "GPS": "No",
    "Radio": "Wireless FM",
    "USB": "Yes"
  },
  "Features": {
    "Messaging": "SMS, MMS, Email",
    "Browser": "WAP",
    "Games": "Yes",
    "Java": "Yes",
    "Others": [
      "SNS applications",
      "Analog TV",
      "MP3 player",
      "Organizer",
      "Unit/currency converter",
      "Voice memo",
      "Predictive text input"
    ]
  },
  "Battery": {
    "Others": "Removable Li-Ion battery",
    "Stand-by": "Up to 192 h",
    "Talk time": "Up to 4 h"
  },
  "Misc": {
    "Colors": "Black/Red, White/Blue"
  }
}