{
  "name": "Vodafone Q3000",
  "description": "XOLO Q3000 Android smartphone. Announced 2013, December. Features 3G, 5.7″ IPS LCD capacitive touchscreen, 13 MP camera, Wi-Fi, GPS, Bluetooth.",
  "url": "http://www.gsmarena.com/xolo_q3000-5927.php",
  "imageUrl": "http://cdn2.gsmarena.com/vv/bigpic/xolo-q3000.jpg",
  "Network": {
    "Technology": "GSM / HSPA",
    "2G bands": "GSM 850 / 900 / 1800 / 1900 - SIM 1 & SIM 2",
    "3G bands": "HSDPA 900 / 1900 / 2100",
    "Speed": "HSPA 42.2/11.5 Mbps",
    "GPRS": "Yes",
    "EDGE": "Yes"
  },
  "Launch": {
    "Announced": "2013, December",
    "Status": "Available. Released 2013, December"
  },
  "Body": {
    "Dimensions": "164.8 x 81.6 x 8.9 mm (6.49 x 3.21 x 0.35 in)",
    "Weight": "-",
    "SIM": "Dual SIM"
  },
  "Display": {
    "Type": "IPS LCD capacitive touchscreen, 16M colors",
    "Size": "5.7 inches (~66.6% screen-to-body ratio)",
    "Resolution": "1080 x 1920 pixels (~386 ppi pixel density)",
    "Multitouch": "Yes"
  },
  "Platform": {
    "OS": "Android OS, v4.2 (Jelly Bean)",
    "Chipset": "Mediatek MT6589",
    "CPU": "Quad-core 1.5 GHz Cortex-A7",
    "GPU": "PowerVR SGX544"
  },
  "Memory": {
    "Card slot": "microSD, up to 32 GB (dedicated slot)",
    "Internal": "16 GB, 2 GB RAM"
  },
  "Camera": {
    "Primary": "13 MP, autofocus, LED flash",
    "Features": "Geo-tagging, touch focus, face detection, HDR, panorama",
    "Video": "1080p@30fps",
    "Secondary": "5 MP"
  },
  "Sound": {
    "Alert types": "Vibration; MP3, WAV ringtones",
    "Loudspeaker ": "Yes",
    "3.5mm jack ": "Yes"
  },
  "Comms": {
    "WLAN": "Wi-Fi 802.11 b/g/n, hotspot",
    "Bluetooth": "v4.0, A2DP",
    "GPS": "Yes, with A-GPS, GLONASS",
    "Radio": "FM radio",
    "USB": "microUSB v2.0, USB Host"
  },
  "Features": {
    "Sensors": "Accelerometer, gyro, proximity, compass",
    "Messaging": "SMS(threaded view), MMS, Email, Push Email, IM",
    "Browser": "HTML5",
    "Java": "No",
    "Others": [
      "Active noise cancellation with dedicated mic",
      "MP4/H.264 player",
      "MP3/WAV/AAC player",
      "Document viewer",
      "Photo/video editor",
      "Voice memo"
    ]
  },
  "Battery": {
    "Others": "Removable Li-Ion 4000 mAh battery",
    "Stand-by": "Up to 667 h",
    "Talk time": "Up to 33 h"
  },
  "Misc": {
    "Colors": "Black, White",
    "SAR EU": "0.37 W/kg (head)     0.53 W/kg (body)",
    "Price group": "5/10 (About 250 EUR)"
  }
}